externalator
