Metadata-Version: 1.0
Name: externalator
Version: 0.7.0
Summary: svn bundle manager
Home-page: http://openplans.org/
Author: The Open Planning Project
Author-email: jhammel@openplans.org,info@openplans.org
License: GPL
Platform: UNKNOWN
